ezconfig_client/__init__.py
ezconfig_client/loader.py
ezconfig_client-0.7.dist-info/LICENSE
ezconfig_client-0.7.dist-info/METADATA
ezconfig_client-0.7.dist-info/WHEEL
ezconfig_client-0.7.dist-info/entry_points.txt
ezconfig_client-0.7.dist-info/top_level.txt
ezconfig_client-0.7.dist-info/RECORD
