Metadata-Version: 2.1
Name: ezconfig-client
Version: 0.7
Summary: ezconfig client
Home-page: https://github.com/riichg5/ezconfig_client
Author: RiichTT
Author-email: tolibo@hotmail.com
Classifier: Programming Language :: Python :: 3
Classifier: License :: OSI Approved :: MIT License
Classifier: Operating System :: OS Independent
License-File: LICENSE
Requires-Dist: requests (>=2.22.0)
Requires-Dist: retrying (>=1.3.4)
